{
  "title": "エコギア シラスヘッド",
  "imgUrl": "https://m.media-amazon.com/images/I/91qrzuB1vTL._AC_SL1500_.jpg",
  "imgWidth": 200,
  "aUrl": "https://www.amazon.co.jp/%E3%82%A8%E3%82%B3%E3%82%AE%E3%82%A2-%E3%82%B7%E3%83%A9%E3%82%B9%E3%83%98%E3%83%83%E3%83%891-16oz-1-8g-5305/dp/B001Q8W6IE?__mk_ja_JP=%E3%82%AB%E3%82%BF%E3%82%AB%E3%83%8A&crid=XN20TAD0S3A4&keywords=%E3%82%A8%E3%82%B3%E3%82%AE%E3%82%A2%2B%E3%82%B7%E3%83%A9%E3%82%B9%E3%83%98%E3%83%83%E3%83%89&qid=1673872995&s=sports&sprefix=%E3%82%A8%E3%82%B3%E3%82%AE%E3%82%A2%2B%E3%82%B7%E3%83%A9%E3%82%B9%E3%83%98%E3%83%83%E3%83%89%2Csporting%2C174&sr=1-1&th=1&psc=1&linkCode=ll1&tag=yusatosh-22&linkId=dfe2fd9c2dfdd98077ce18fc7ea5c34c&language=ja_JP&ref_=as_li_ss_tl",
  "yUrl": "https://shopping.yahoo.co.jp/search?first=1&ss_first=1&ts=1673873168&mcr=a3d1d5141ba900c2c7a61e504cbb80c9&tab_ex=commerce&uIv=on&sretry=1&area=27&astk=&aq=&oq=&p=%E3%82%A8%E3%82%B3%E3%82%AE%E3%82%A2+%E3%82%B7%E3%83%A9%E3%82%B9%E3%83%98%E3%83%83%E3%83%89+-%E3%83%95%E3%82%A1%E3%82%A4%E3%83%B3&sc_i=shp_pc_search_searchBox_2",
  "rUrl": "https://search.rakuten.co.jp/search/mall/エコギア シラスヘッド /?nitem=ファイン/",
  "btnStyle": "__three",
  "desc": ""
}