{
  "title": "メガバス VATISSA",
  "imgUrl": "https://m.media-amazon.com/images/I/31KsUIwGvzL._AC_SX679_.jpg",
  "imgWidth": 200,
  "aUrl": "https://www.amazon.co.jp/gp/product/B06XJMC373",
  "yUrl": "https://shopping.yahoo.co.jp/search?first=1&ss_first=1&ts=1674783342&mcr=a6cb261abafbdc4efe6ee96646d2b627&tab_ex=commerce&sretry=0&area=27&astk=&aq=&oq=&p=vatissa&sc_i=shp_pc_search_searchBox_2",
  "rUrl": "https://search.rakuten.co.jp/search/mall/VATISSA/",
  "btnStyle": "__three",
  "desc": ""
}