{
  "title": "パズデザイン 透湿防水レインウェア&ウェーダー 補修用リペアシート PAC-276",
  "imgUrl": "https://m.media-amazon.com/images/I/81-vC1+CM8L._AC_SX679_.jpg",
  "imgWidth": 200,
  "aUrl": "https://www.amazon.co.jp/%E3%83%91%E3%82%BA%E3%83%87%E3%82%B6%E3%82%A4%E3%83%B3-Pazdesign-%E9%80%8F%E6%B9%BF%E9%98%B2%E6%B0%B4%E3%83%AC%E3%82%A4%E3%83%B3%E3%82%A6%E3%82%A7%E3%82%A2%EF%BC%86%E3%82%A6%E3%82%A7%E3%83%BC%E3%83%80%E3%83%BC-%E8%A3%9C%E4%BF%AE%E7%94%A8%E3%83%AA%E3%83%9A%E3%82%A2%E3%82%B7%E3%83%BC%E3%83%88-PAC-276/dp/B07MXB3HGP?__mk_ja_JP=%E3%82%AB%E3%82%BF%E3%82%AB%E3%83%8A&crid=3W3FG4NN3IEVD&keywords=%E3%83%A2%E3%83%B3%E3%83%99%E3%83%AB+%E3%82%B4%E3%82%A2%E3%83%86%E3%83%83%E3%82%AF%E3%82%B9+%E8%A3%9C%E4%BF%AE%E3%82%B7%E3%83%BC%E3%83%88&qid=1699275309&s=sports&sprefix=%E3%83%A2%E3%83%B3%E3%83%99%E3%83%AB+%E3%82%B4%E3%82%A2%E3%83%86%E3%83%83%E3%82%AF%E3%82%B9+%E8%A3%9C%E4%BF%AE%E3%82%B7%E3%83%BC%E3%83%88%2Csporting%2C138&sr=1-19&linkCode=ll1&tag=yusatosh-22&linkId=be2c9174c64d9b76788da39ceabbfe0f&language=ja_JP&ref_=as_li_ss_tl",
  "yUrl": "https://shopping.yahoo.co.jp/search?p=%E3%83%91%E3%82%BA%E3%83%87%E3%82%B6%E3%82%A4%E3%83%B3+PAC-276&ss_first=1&tab_ex=commerce&area=27&prom=1&X=12&sc_i=shp_pc_search_sort_sortitem",
  "rUrl": "https://search.rakuten.co.jp/search/mall/パズデザイン PAC-276/",
  "btnStyle": "__three",
  "desc": ""
}