{
  "title": "シマノ 夢屋 19 カスタムスプール 1000 カーディフ",
  "imgUrl": "https://m.media-amazon.com/images/I/31p3P2e1r3L._AC_.jpg",
  "imgWidth": 200,
  "aUrl": "https://www.amazon.co.jp/%E3%82%B7%E3%83%9E%E3%83%8E-SHIMANO-%E3%82%AB%E3%82%B9%E3%82%BF%E3%83%A0%E3%82%B9%E3%83%97%E3%83%BC%E3%83%AB-N2010%E3%82%B9%E3%83%97%E3%83%BC%E3%83%AB-%E3%82%AB%E3%83%BC%E3%83%87%E3%82%A3%E3%83%95%E3%82%AB%E3%83%A9%E3%83%BC/dp/B07MX1F36L?__mk_ja_JP=%E3%82%AB%E3%82%BF%E3%82%AB%E3%83%8A&dchild=1&keywords=%E5%A4%A2%E5%B1%8B%E3%82%AB%E3%82%B9%E3%82%BF%E3%83%A0%E3%82%B9%E3%83%97%E3%83%BC%E3%83%AB%2B1000%2B%E3%82%AB%E3%83%BC%E3%83%87%E3%82%A3%E3%83%95&qid=1617430092&sr=8-1&th=1&linkCode=ll1&tag=yusatosh-22&linkId=014489eb679780aa0d660edfec5d5c95&language=ja_JP&ref_=as_li_ss_tl",
  "yUrl": "https://shopping.yahoo.co.jp/products/z4gk2hsq8f?sc_i=shp_pc_search_itemlist_shsrg_products",
  "rUrl": "https://product.rakuten.co.jp/product/-/7b9e3c087e4e531854613b9898dc8313",
  "btnStyle": "__three",
  "desc": ""
}