{
  "title": "シマノ ソアレXR S76UL-T",
  "imgUrl": "https://m.media-amazon.com/images/I/41P7gSRDreL._AC_SX679_.jpg",
  "imgWidth": 200,
  "aUrl": "https://www.amazon.co.jp/%E3%82%B7%E3%83%9E%E3%83%8E-SHIMANO-%E3%83%AD%E3%83%83%E3%83%89-%E3%82%BD%E3%82%A2%E3%83%AC-S510L-S/dp/B09F3MLRFZ?pd_rd_w=5vuCg&content-id=amzn1.sym.d769922e-188a-40cc-a180-3315f856e8d6&pf_rd_p=d769922e-188a-40cc-a180-3315f856e8d6&pf_rd_r=0AHBGRZ8CBAT4EW7K3T1&pd_rd_wg=KqnwS&pd_rd_r=df83a855-6d8b-4ab4-9c5a-c62408d8cc2c&pd_rd_i=B09KTKVPVV&th=1&linkCode=ll1&tag=yusatosh-22&linkId=c2278af8afa4bf09900fdeae1ff06168&language=ja_JP&ref_=as_li_ss_tl",
  "yUrl": "https://shopping.yahoo.co.jp/products/0ed8171b3e?sc_i=shp_pc_search_itemlist_shsrg_products",
  "rUrl": "https://search.rakuten.co.jp/search/mall/ソアレ XR S76UL-T/",
  "btnStyle": "__three",
  "desc": ""
}